README.md
setup.py
src/AirobotLibrary.egg-info/PKG-INFO
src/AirobotLibrary.egg-info/SOURCES.txt
src/AirobotLibrary.egg-info/dependency_links.txt
src/AirobotLibrary.egg-info/requires.txt
src/AirobotLibrary.egg-info/top_level.txt
src/airobotLibrary/__init__.py
src/airobotLibrary/air_appium.py
src/airobotLibrary/air_selenium.py