Metadata-Version: 2.1
Name: AirobotLibrary
Version: 1.1.6
Summary: Robotframework Library For Airobot Test Framework
Home-page: https://github.com/BSTester/AirobotLibrary
Author: 贝克街的捉虫师
Author-email: forpeng@foxmail.com
License: UNKNOWN
Project-URL: Source, https://github.com/BSTester/AirobotLibrary
Keywords: airtest,robotframework,selenium
Platform: UNKNOWN
Classifier: Development Status :: 4 - Beta
Classifier: Intended Audience :: Developers
Classifier: Topic :: Software Development :: Build Tools
Classifier: License :: OSI Approved :: MIT License
Classifier: Programming Language :: Python :: 3.6
Classifier: Programming Language :: Python :: 3.7
Classifier: Programming Language :: Python :: 3.8
Classifier: Programming Language :: Python :: 3.9
Classifier: Programming Language :: Python :: 3 :: Only
Requires-Python: >=3.5, <4
